{"title": "Camparinha", "pack": "Nightcap", "flavors": ["sweet", "bitter"], "labels": ["Drinks", "Bitter", "Spirit Forward", "Dry", "Dinner", "Nightcap"], "glass": "none", "ingredients": [{"amount": 2, "measurement": "oz", "ingredient": "campari", "type": "main", "notes": "none"}, {"amount": 1, "measurement": "", "ingredient": "lime", "type": "main", "notes": "cut in 8 pieces"}, {"amount": 0.5, "measurement": "oz", "ingredient": "simple syrup", "type": "main", "notes": "none"}, {"amount": 0.25, "measurement": "oz", "ingredient": "white agricole rhum", "type": "main", "notes": "none"}], "instructions": "Muddle Lime with Campari\nAdd rhum and simple syrup\nAdd crushed ice and stir", "information": " https://www.youtube.com/watch?v=Sp_yFcWMQqI"}