{"title": "Surfer on Acid", "pack": "Dinner", "flavors": ["sweet", "fresh"], "labels": ["Drinks", "Bitter", "Sweet", "Dinner"], "glass": "rocks", "ingredients": [{"amount": 1, "measurement": "oz", "ingredient": "jagermeister", "type": "main", "notes": "none"}, {"amount": 1, "measurement": "oz", "ingredient": "pineapple rum", "type": "main", "notes": "plantation"}, {"amount": 1, "measurement": "oz", "ingredient": "pineapple juice", "type": "main", "notes": "none"}, {"amount": 0.5, "measurement": "oz", "ingredient": "orgeat", "type": "main", "notes": "none"}, {"amount": 0.5, "measurement": "oz", "ingredient": "lime juice", "type": "main", "notes": "none"}, {"amount": "", "measurement": "", "ingredient": "pineapple frond", "type": "garnish", "notes": "none"}], "instructions": "Shake and pour over ice in Double Old Fashioned", "information": "https://www.youtube.com/watch?v=nfN_CAcySGo"}