{"title": "The Ghost of Black's Beach", "pack": "Tiki", "flavors": ["herbal", "fresh"], "labels": ["Drinks", "Bitter", "Tiki", "Dry", "Dinner"], "glass": "rocks", "ingredients": [{"amount": 2, "measurement": "oz", "ingredient": "jamaican rum", "type": "main", "notes": "none"}, {"amount": 0.75, "measurement": "oz", "ingredient": "lemon juice", "type": "main", "notes": "none"}, {"amount": 0.375, "measurement": "oz", "ingredient": "velvet falernum", "type": "main", "notes": "none"}, {"amount": 0.375, "measurement": "oz", "ingredient": "benedictine", "type": "main", "notes": "none"}, {"amount": "", "measurement": "", "ingredient": "pineapple frond", "type": "garnish", "notes": "none"}], "instructions": "Whip shake and pack with crushed ice in a rocks glass. ", "information": "https://www.youtube.com/watch?v=FbBhiSI3q-o"}