{"color":"BROWN","isTrashed":false,"isPinned":false,"isArchived":true,"annotations":[{"description":"\u201cJagermeister is nice burned,\u201d says Dave Arnold. \u201cA lot of bitter liqueurs are nice when they are burned.\u201d For this drink, he applies a flame to ca","source":"WEBLINK","title":"Flaming Jäger Cocktail Recipe | PUNCH","url":"https://punchdrink.com/recipes/flaming-jager/"}],"textContent":"2 teaspoons sugar\n2 ounces Jägermeister\n1/4 ounce lemon juice\n1 pinch salt\n2 ounces water\nGarnish: orange twist\n\nHeat sugar in a saucepan, until caramelized.\nAdd Jägermeister, lemon juice and salt to pan.\nUse a long-handled match or kitchen torch to apply flame to the contents of the pan; it should catch fire.\nAdd water, dousing the fire. Add more water if needed to extinguish the flame.\nScrape the insides of the pan and briefly stir to combine.\nPour into mug and garnish with orange twist.\n\nhttps://punchdrink.com/recipes/flaming-jager/","title":"Flaming Jager","userEditedTimestampUsec":1582782335963000,"labels":[{"name":"Drinks"},{"name":"Bitter"},{"name":"Spirit Forward"},{"name":"Hot Drinks"},{"name":"Nightcap"}]}